fRAT/.DS_Store
fRAT/HOUSE/__init__.py
fRAT/HOUSE/add_motion.py
fRAT/HOUSE/add_noise.py
fRAT/HOUSE/handler.py
fRAT/HOUSE/separate_noise_volumes.py
fRAT/__main__.py
fRAT/_version.py
fRAT/configuration_profiles/latest_settings.toml
fRAT/configuration_profiles/maps/default_config.toml
fRAT/configuration_profiles/maps/statmap_config.toml
fRAT/configuration_profiles/maps/test_config.toml
fRAT/configuration_profiles/roi_analysis/default_config.toml
fRAT/configuration_profiles/roi_analysis/fRAT_config.toml
fRAT/configuration_profiles/roi_analysis/test_config.toml
fRAT/images/fRAT.gif
fRAT/nogui.py
fRAT/utils/.DS_Store
fRAT/utils/__init__.py
fRAT/utils/analysis.py
fRAT/utils/bootstrap.css
fRAT/utils/dash_report.py
fRAT/utils/directory_comparison.py
fRAT/utils/fRAT_config_setup.py
fRAT/utils/figures.py
fRAT/utils/html_report.py
fRAT/utils/printResults.py
fRAT/utils/script.js
fRAT/utils/statistics.py
fRAT/utils/statmap.py
fRAT/utils/statmap_config_setup.py
fRAT/utils/utils.py
frat_brain-1.6.5.dist-info/LICENSE
frat_brain-1.6.5.dist-info/WHEEL
frat_brain-1.6.5.dist-info/entry_points.txt
frat_brain-1.6.5.dist-info/METADATA
frat_brain-1.6.5.dist-info/RECORD
