Metadata-Version: 2.1
Name: frat-brain
Version: 1.6.5
Summary: Application for ROI fMRI data analysis.
Home-page: https://fmri-roi-analysis-tool.readthedocs.io/en/latest/
Author: Elliot Howley
Author-email: elliohow@hotmail.com
Requires-Python: >=3.10,<3.11
Classifier: Programming Language :: Python :: 3
Classifier: Programming Language :: Python :: 3.10
Requires-Dist: altgraph (==0.17.2)
Requires-Dist: bootstrapped (==0.0.2)
Requires-Dist: brotli (==1.0.9)
Requires-Dist: certifi (==2022.12.7)
Requires-Dist: chardet (==3.0.4)
Requires-Dist: charset-normalizer (==2.0.12)
Requires-Dist: ci-info (==0.2.0)
Requires-Dist: click (==7.1.1)
Requires-Dist: contourpy (==1.0.7)
Requires-Dist: cycler (==0.10.0)
Requires-Dist: cython (==0.29.21)
Requires-Dist: dash (==1.19.0)
Requires-Dist: dash-core-components (==1.15.0)
Requires-Dist: dash-html-components (==1.1.2)
Requires-Dist: dash-renderer (==1.9.0)
Requires-Dist: dash-table (==4.11.2)
Requires-Dist: dataclasses (==0.6)
Requires-Dist: decorator (==4.4.2)
Requires-Dist: descartes (==1.1.0)
Requires-Dist: dill (==0.3.6)
Requires-Dist: dominate (==2.6.0)
Requires-Dist: etelemetry (==0.2.2)
Requires-Dist: filelock (==3.0.12)
Requires-Dist: flask (==1.1.2)
Requires-Dist: flask-compress (==1.8.0)
Requires-Dist: fonttools (==4.38.0)
Requires-Dist: fslpy (==3.4.0)
Requires-Dist: funcsigs (==1.0.2)
Requires-Dist: future (==0.18.2)
Requires-Dist: gevent (==22.10.2)
Requires-Dist: greenlet (==2.0.2)
Requires-Dist: h5py (==3.8.0)
Requires-Dist: idna (==2.9)
Requires-Dist: imageio (==2.9.0)
Requires-Dist: isodate (==0.6.0)
Requires-Dist: itsdangerous (==1.1.0)
Requires-Dist: jinja2 (==2.11.3)
Requires-Dist: joblib (==1.2.0)
Requires-Dist: kiwisolver (==1.4.4)
Requires-Dist: looseversion (==1.0.1)
Requires-Dist: lxml (==4.9.2)
Requires-Dist: macholib (==1.15.2)
Requires-Dist: markupsafe (==1.1.1)
Requires-Dist: matplotlib (==3.6.3)
Requires-Dist: mizani (==0.8.1)
Requires-Dist: multiprocess (==0.70.14)
Requires-Dist: networkx (==2.4)
Requires-Dist: neurdflib (==5.0.1)
Requires-Dist: nibabel (==3.2.1)
Requires-Dist: nilearn (==0.9.0)
Requires-Dist: nipype (==1.8.4)
Requires-Dist: numpy (==1.22.3)
Requires-Dist: packaging (==23.0)
Requires-Dist: palettable (==3.3.0)
Requires-Dist: pandas (==1.5.3)
Requires-Dist: pathos (==0.2.6)
Requires-Dist: patsy (==0.5.3)
Requires-Dist: pillow (==9.3.0)
Requires-Dist: pip-autoremove (==0.10.0)
Requires-Dist: plotly (==4.14.3)
Requires-Dist: plotnine (==0.10.1)
Requires-Dist: pox (==0.2.8)
Requires-Dist: ppft (==1.6.6.2)
Requires-Dist: prov (==1.5.3)
Requires-Dist: pydot (==1.4.1)
Requires-Dist: pydotplus (==2.0.2)
Requires-Dist: pyinstaller (==4.9)
Requires-Dist: pyinstaller-hooks-contrib (==2022.2)
Requires-Dist: pyparsing (==2.4.6)
Requires-Dist: python-dateutil (==2.8.1)
Requires-Dist: pytz (==2022.7.1)
Requires-Dist: pywavelets (==1.4.1)
Requires-Dist: rdflib (==5.0.0)
Requires-Dist: requests (==2.27.1)
Requires-Dist: retrying (==1.3.3)
Requires-Dist: scikit-image (==0.19.3)
Requires-Dist: scikit-learn (==1.2.1)
Requires-Dist: scipy (==1.10.0)
Requires-Dist: simplejson (==3.17.0)
Requires-Dist: six (==1.14.0)
Requires-Dist: sklearn (==0.0)
Requires-Dist: statsmodels (==0.13.5)
Requires-Dist: tabulate (==0.8.9)
Requires-Dist: tenacity (==8.2.0)
Requires-Dist: threadpoolctl (==2.1.0)
Requires-Dist: tifffile (==2021.7.30)
Requires-Dist: toml (==0.10.2)
Requires-Dist: traits (==6.3.2)
Requires-Dist: urllib3 (==1.26.5)
Requires-Dist: werkzeug (==1.0.1)
Requires-Dist: xlrd (==1.2.0)
Requires-Dist: xmltodict (==0.12.0)
Requires-Dist: zope-event (==4.5.0)
Requires-Dist: zope-interface (==5.2.0)
Project-URL: Repository, https://github.com/elliohow/fMRI_ROI_Analysis_Tool
